emotiefflib/__init__.py
emotiefflib/engagement_classification_model.py
emotiefflib/facial_analysis.py
emotiefflib/utils.py
emotiefflib-1.0.dist-info/LICENSE
emotiefflib-1.0.dist-info/METADATA
emotiefflib-1.0.dist-info/WHEEL
emotiefflib-1.0.dist-info/top_level.txt
emotiefflib-1.0.dist-info/RECORD
